LICENSE
MANIFEST.in
README.rst
setup.py
nos/__init__.py
nos/compat.py
nos/connection.py
nos/exceptions.py
nos/serializer.py
nos/transport.py
nos/client/__init__.py
nos/client/auth.py
nos/client/nos_client.py
nos/client/utils.py
nos_python_sdk.egg-info/PKG-INFO
nos_python_sdk.egg-info/SOURCES.txt
nos_python_sdk.egg-info/dependency_links.txt
nos_python_sdk.egg-info/requires.txt
nos_python_sdk.egg-info/top_level.txt
test_nos/__init__.py
test_nos/run_tests.py
test_nos/simple_test.py
test_nos/test_cases.py
test_nos/test_connection.py
test_nos/test_exceptions.py
test_nos/test_serializer.py
test_nos/test_smoke_test.py
test_nos/test_transport.py
test_nos/test_client/__init__.py
test_nos/test_client/test_auth.py
test_nos/test_client/test_nos_client.py