Metadata-Version: 1.1
Name: nos-python-sdk
Version: 1.0.1
Summary: NetEase Object Storage SDK
Home-page: https://c.163.com/
Author: NOS Developer
Author-email: hzsunjianliang@corp.netease.com
License: MIT License
Platform: UNKNOWN
Classifier: Development Status :: 5 - Production/Stable
Classifier: License :: OSI Approved :: MIT License
Classifier: Intended Audience :: Developers
Classifier: Operating System :: OS Independent
Classifier: Programming Language :: Python
Classifier: Programming Language :: Python :: 2
Classifier: Programming Language :: Python :: 2.6
Classifier: Programming Language :: Python :: 2.7
